{
    "schemaVersion": 1,
    "id": "prometheus",
    "version": "${version}",
    "name": "prometheus",
    "description": "",
    "authors": [],
    "contact": {},
    "license": "MIT",
    "icon": "icon.png",
    "environment": "*",
    "entrypoints": {
        "main": [
            "earth.terrarium.prometheus.fabric.PrometheusFabric"
        ],
        "client": [
            "earth.terrarium.prometheus.client.fabric.PrometheusFabricClient",
            "earth.terrarium.prometheus.Prometheus::postInit"
        ],
        "server": [
            "earth.terrarium.prometheus.Prometheus::postInit"
        ]
    },
    "mixins": [
        "prometheus.mixins.json",
        "prometheus-common.mixins.json"
    ],
    "depends": {
        "fabricloader": ">=0.14.19",
        "minecraft": ">=1.19.4"
    }
}
